sgdml/__init__.py
sgdml/cli.py
sgdml/get.py
sgdml/predict.py
sgdml/torchtools.py
sgdml/train.py
sgdml/intf/__init__.py
sgdml/intf/ase_calc.py
sgdml/solvers/__init__.py
sgdml/solvers/analytic.py
sgdml/solvers/iterative.py
sgdml/utils/__init__.py
sgdml/utils/desc.py
sgdml/utils/io.py
sgdml/utils/perm.py
sgdml/utils/ui.py
sgdml-1.0.3.data/scripts/sgdml_dataset_from_aims.py
sgdml-1.0.3.data/scripts/sgdml_dataset_from_extxyz.py
sgdml-1.0.3.data/scripts/sgdml_dataset_from_ipi.py
sgdml-1.0.3.data/scripts/sgdml_dataset_to_extxyz.py
sgdml-1.0.3.data/scripts/sgdml_dataset_via_ase.py
sgdml-1.0.3.data/scripts/sgdml_datasets_from_model.py
sgdml-1.0.3.dist-info/LICENSE.txt
sgdml-1.0.3.dist-info/METADATA
sgdml-1.0.3.dist-info/WHEEL
sgdml-1.0.3.dist-info/entry_points.txt
sgdml-1.0.3.dist-info/top_level.txt
sgdml-1.0.3.dist-info/RECORD
