Metadata-Version: 2.1
Name: sgdml
Version: 1.0.3
Summary: Reference implementation of the GDML and sGDML force field models.
Home-page: http://www.sgdml.org
Author: Stefan Chmiela
Author-email: sgdml@chmiela.com
License: LICENSE.txt
Classifier: Development Status :: 4 - Beta
Classifier: Environment :: Console
Classifier: Intended Audience :: Science/Research
Classifier: Intended Audience :: Education
Classifier: Intended Audience :: Developers
Classifier: License :: OSI Approved :: MIT License
Classifier: Operating System :: MacOS :: MacOS X
Classifier: Operating System :: POSIX :: Linux
Classifier: Programming Language :: Python :: 3.7
Classifier: Topic :: Scientific/Engineering :: Chemistry
Classifier: Topic :: Scientific/Engineering :: Physics
Classifier: Topic :: Software Development :: Libraries :: Python Modules
License-File: LICENSE.txt
Requires-Dist: torch >=1.8
Requires-Dist: numpy >=1.19.0
Requires-Dist: scipy >=1.1.0
Requires-Dist: psutil
Requires-Dist: future
Provides-Extra: ase
Requires-Dist: ase >=3.16.2 ; extra == 'ase'
